chippy/__init__.py
chippy/__main__.py
chippy/app.py
chippy/chippy.py
chippy/clock.py
chippy/code.py
chippy/config.py
chippy/debug.py
chippy/errors.py
chippy/processor.py
chippy/status.py
chippy/window.py
chippy/data/chime.wav
chippy/roms/15PUZZLE
chippy/roms/BLINKY
chippy/roms/BLITZ
chippy/roms/BRIX
chippy/roms/CONNECT4
chippy/roms/GUESS
chippy/roms/HIDDEN
chippy/roms/INVADERS
chippy/roms/KALEID
chippy/roms/MAZE
chippy/roms/MERLIN
chippy/roms/MISSILE
chippy/roms/PONG
chippy/roms/PONG2
chippy/roms/PUZZLE
chippy/roms/SYZYGY
chippy/roms/TANK
chippy/roms/TETRIS
chippy/roms/TICTAC
chippy/roms/UFO
chippy/roms/VBRIX
chippy/roms/VERS
chippy/roms/WIPEOFF
chippy_emu-0.1.4.dist-info/LICENSE
chippy_emu-0.1.4.dist-info/METADATA
chippy_emu-0.1.4.dist-info/WHEEL
chippy_emu-0.1.4.dist-info/top_level.txt
chippy_emu-0.1.4.dist-info/RECORD
